chaosistio/__init__.py
chaosistio/fault/__init__.py
chaosistio/fault/actions.py
chaosistio/fault/probes.py
chaostoolkit_istio-0.4.1.dist-info/METADATA
chaostoolkit_istio-0.4.1.dist-info/WHEEL
chaostoolkit_istio-0.4.1.dist-info/licenses/LICENSE
chaostoolkit_istio-0.4.1.dist-info/RECORD
